py4swiss/__init__.py
py4swiss/dynamicuint.cpython-311-x86_64-linux-musl.so
py4swiss/dynamicuint.pyi
py4swiss/main.py
py4swiss/matching_computer.cpython-311-x86_64-linux-musl.so
py4swiss/matching_computer.pyi
py4swiss/engines/__init__.py
py4swiss/engines/burstein/__init__.py
py4swiss/engines/burstein/bracket.py
py4swiss/engines/burstein/bye_matcher.py
py4swiss/engines/burstein/engine.py
py4swiss/engines/burstein/pairer.py
py4swiss/engines/burstein/player.py
py4swiss/engines/burstein/state.py
py4swiss/engines/burstein/criteria/__init__.py
py4swiss/engines/burstein/criteria/absolute/__init__.py
py4swiss/engines/burstein/criteria/absolute/c1.py
py4swiss/engines/burstein/criteria/absolute/c2.py
py4swiss/engines/burstein/criteria/absolute/c3.py
py4swiss/engines/burstein/criteria/color/__init__.py
py4swiss/engines/burstein/criteria/color/e1.py
py4swiss/engines/burstein/criteria/color/e2.py
py4swiss/engines/burstein/criteria/color/e3.py
py4swiss/engines/burstein/criteria/color/e4.py
py4swiss/engines/burstein/criteria/color/e5.py
py4swiss/engines/burstein/criteria/quality/__init__.py
py4swiss/engines/burstein/criteria/quality/c5.py
py4swiss/engines/burstein/criteria/quality/c6.py
py4swiss/engines/burstein/criteria/quality/c7.py
py4swiss/engines/burstein/criteria/quality/c8.py
py4swiss/engines/common/__init__.py
py4swiss/engines/common/color_preference.py
py4swiss/engines/common/exceptions.py
py4swiss/engines/common/float.py
py4swiss/engines/common/pairing.py
py4swiss/engines/common/pairing_engine.py
py4swiss/engines/dubov/__init__.py
py4swiss/engines/dubov/bracket.py
py4swiss/engines/dubov/bye_matcher.py
py4swiss/engines/dubov/engine.py
py4swiss/engines/dubov/pairer.py
py4swiss/engines/dubov/player.py
py4swiss/engines/dubov/state.py
py4swiss/engines/dubov/criteria/__init__.py
py4swiss/engines/dubov/criteria/absolute/__init__.py
py4swiss/engines/dubov/criteria/absolute/c1.py
py4swiss/engines/dubov/criteria/absolute/c2.py
py4swiss-0.3.1.dist-info/METADATA
py4swiss-0.3.1.dist-info/WHEEL
py4swiss-0.3.1.dist-info/entry_points.txt
py4swiss-0.3.1.dist-info/top_level.txt
py4swiss-0.3.1.dist-info/RECORD
py4swiss-0.3.1.dist-info/licenses/LICENSE
py4swiss-0.3.1.dist-info/sboms/auditwheel.cdx.json
