Metadata-Version: 2.4
Name: py4swiss
Version: 0.3.1
Summary: A package to pair swiss tournaments
Author-email: Moritz Eckert <MoritzEckert@web.de>
License: MIT
Project-URL: Homepage, https://github.com/Moritz72/py4swiss
Project-URL: Repository, https://github.com/Moritz72/py4swiss
Keywords: swiss,pairing,chess,tournament
Classifier: Programming Language :: Python :: 3
Classifier: Programming Language :: Python :: 3.11
Classifier: License :: OSI Approved :: MIT License
Classifier: Operating System :: OS Independent
Classifier: Topic :: Games/Entertainment :: Board Games
License-File: LICENSE
Requires-Dist: pydantic>=2.11.9
Provides-Extra: dev
Requires-Dist: pytest>=7.2; extra == "dev"
Requires-Dist: pytest-cov>=7.0.0; extra == "dev"
Requires-Dist: mypy>=1.0; extra == "dev"
Requires-Dist: ruff>=0.14; extra == "dev"
Requires-Dist: black>=24.0; extra == "dev"
Dynamic: license-file
